{
  "animateLoading": true,
  "borderRadius": "{{appsmith.theme.borderRadius.appBorderRadius}}",
  "bottomRow": 6,
  "boxShadow": "none",
  "buttonColor": "{{appsmith.theme.colors.primaryColor}}",
  "buttonVariant": "PRIMARY",
  "dynamicBindingPathList": [
    {
      "key": "buttonColor"
    },
    {
      "key": "borderRadius"
    }
  ],
  "iconName": "plus",
  "isDisabled": false,
  "isLoading": false,
  "isVisible": true,
  "key": "52h1n3hlg8",
  "leftColumn": 56,
  "minWidth": 50,
  "mobileBottomRow": 6,
  "mobileLeftColumn": 26,
  "mobileRightColumn": 30,
  "mobileTopRow": 2,
  "needsErrorInfo": false,
  "parentColumnSpace": 11.875,
  "parentId": "0",
  "parentRowSpace": 10,
  "renderMode": "CANVAS",
  "responsiveBehavior": "hug",
  "rightColumn": 60,
  "topRow": 2,
  "type": "ICON_BUTTON_WIDGET",
  "version": 1,
  "widgetId": "asa8ph5a65",
  "widgetName": "IconButton1"
}